yea_wandb/__init__.py
yea_wandb/artifact_emu.py
yea_wandb/backend.py
yea_wandb/hook.py
yea_wandb/mitm.py
yea_wandb/mock_requests.py
yea_wandb/mock_server.py
yea_wandb/plugin.py
yea_wandb/setup.py
yea_wandb-0.9.23.dist-info/LICENSE
yea_wandb-0.9.23.dist-info/METADATA
yea_wandb-0.9.23.dist-info/WHEEL
yea_wandb-0.9.23.dist-info/entry_points.txt
yea_wandb-0.9.23.dist-info/top_level.txt
yea_wandb-0.9.23.dist-info/RECORD
