Metadata-Version: 2.1
Name: yea-wandb
Version: 0.9.23
Summary: Test harness wandb plugin
License: MIT license
Requires-Python: >=3.8
License-File: LICENSE
Requires-Dist: Flask
Requires-Dist: requests
Requires-Dist: responses
Requires-Dist: pandas
Requires-Dist: yea ==0.9.2
